pocar/OneCallApi.py
pocar/OneCallApiAlerts.py
pocar/OneCallApiCurrent.py
pocar/OneCallApiDaily.py
pocar/OneCallApiHourly.py
pocar/OneCallApiMinutely.py
pocar/__init__.py
pocar-0.1.dist-info/LICENSE
pocar-0.1.dist-info/METADATA
pocar-0.1.dist-info/WHEEL
pocar-0.1.dist-info/top_level.txt
pocar-0.1.dist-info/RECORD
