Metadata-Version: 2.1
Name: pocar
Version: 0.1
Summary: Process Open Weather data provided by One Call API response.
Home-page: https://github.com/tiagosarmento/pocar
Author: Tiago Santos
Author-email: tiagosarmentosantos@gmail.com
License: MIT
Keywords: openweather onecallapi python
Platform: UNKNOWN
Classifier: License :: OSI Approved :: MIT License
Classifier: Programming Language :: Python
Classifier: Programming Language :: Python :: 3.6
Classifier: Programming Language :: Python :: 3.7
Classifier: Programming Language :: Python :: 3.8
Classifier: Programming Language :: Python :: 3.9
Classifier: Natural Language :: English
Classifier: Operating System :: OS Independent
Classifier: Development Status :: 1 - Planning
Classifier: Intended Audience :: Developers
Classifier: Topic :: Software Development :: Libraries
Requires-Python: >=3.6
License-File: LICENSE
Requires-Dist: DateTime
Requires-Dist: requests
